{
  "description": "项目配置文件",
  "packOptions": {
    "ignore": []
  },
  "setting": {
    "urlCheck": false,
    "es6": true,
    "enhance": true,
    "postcss": true,
    "preloadBackgroundData": false,
    "minified": true,
    "newFeature": false,
    "coverView": true,
    "nodeModules": false,
    "autoAudits": false,
    "showShadowRootInWxmlPanel": true,
    "scopeDataCheck": false,
    "uglifyFileName": false,
    "checkInvalidKey": true,
    "checkSiteMap": true,
    "uploadWithSourceMap": true,
    "compileHotReLoad": true,
    "lazyloadPlaceholderEnable": false,
    "useMultiFrameRuntime": true,
    "useApiHook": true,
    "useApiHostProcess": true,
    "babelSetting": {
      "ignore": [],
      "disablePlugins": [],
      "outputPath": ""
    },
    "useIsolateContext": true,
    "userConfirmedBundleSwitch": false,
    "packNpmManually": false,
    "packNpmRelationList": [],
    "minifyWXSS": false,
    "disableUseStrict": false,
    "minifyWXML": true,
    "showES6CompileOption": false,
    "useCompilerPlugins": false,
    "ignoreUploadUnusedFiles": true
  },
  "compileType": "miniprogram",
  "libVersion": "2.23.1",
  "appid": "wxd3b248ee33239fff",
  "projectname": "example",
  "debugOptions": {
    "hidedInDevtools": []
  },
  "scripts": {},
  "staticServerOptions": {
    "baseURL": "",
    "servePath": ""
  },
  "isGameTourist": false,
  "condition": {
    "search": {
      "list": []
    },
    "conversation": {
      "list": []
    },
    "game": {
      "list": []
    },
    "plugin": {
      "list": []
    },
    "gamePlugin": {
      "list": []
    },
    "miniprogram": {
      "list": []
    }
  }
}